{"i.instagram.com":{"/":{"rur":{"key":"rur","value":"FTW","domain":"i.instagram.com","path":"/","secure":true,"httpOnly":true,"hostOnly":true,"creation":"2019-02-04T09:20:31.655Z","lastAccessed":"2019-02-04T09:20:31.655Z"},"mid":{"key":"mid","value":"XFgD3wABAAGulK65hG2pLpdn3kqx","expires":"2029-02-01T09:20:31.000Z","maxAge":315360000,"domain":"i.instagram.com","path":"/","secure":true,"hostOnly":true,"creation":"2019-02-04T09:20:31.657Z","lastAccessed":"2019-02-04T09:20:31.657Z"}}}}srftoken":{"key":"csrftoken","value":"RFBz2qOl0yiNDN9qbuvwMhnJ3hITUCyB","expires":"2020-02-03T09:20:31.000Z","maxAge":31449600,"domain":"i.instagram.com","path":"/","secure":true,"hostOnly":true,"creation":"2019-02-04T09:20:31.657Z","lastAccessed":"2019-02-04T09:20:31.657Z"}}}}